LICENSE
README.md
setup.py
backports/interpreters.py
backports.interpreters.egg-info/PKG-INFO
backports.interpreters.egg-info/SOURCES.txt
backports.interpreters.egg-info/dependency_links.txt
backports.interpreters.egg-info/namespace_packages.txt
backports.interpreters.egg-info/requires.txt
backports.interpreters.egg-info/top_level.txt
backports/interpreters/xxx.c